{"_id":{"$oid":"67cd250375493c24503ec816"},"img":"https://xstore.8theme.com/elementor/demos/rental-car/wp-content/uploads/sites/81/2022/07/Image_7-1-600x316.jpg","category":"Toyota Cayenne","brandId":{"$oid":"67cd240be895c5e5487f531f"},"pricePerDay":42,"des":"Amet facilisi elit quam sollicitudin neque, imperdiet mauris.","__v":0,"updatedAt":{"$date":"2025-03-24T09:02:29.357Z"}}
{"_id":{"$oid":"67cd2777e618cfc69401f482"},"img":"https://xstore.8theme.com/elementor/demos/rental-car/wp-content/uploads/sites/81/2022/07/Image_5-1-600x316.jpg","category":"Aston Martin DB9","brandId":{"$oid":"67cd244ce895c5e5487f5325"},"pricePerDay":24,"des":"Hendrerit vivamus justo maecenas senectus aliquam.","__v":0}
{"_id":{"$oid":"67ce92df426de9e0ddc8332e"},"img":"https://xstore.b-cdn.net/elementor/demos/rental-car/wp-content/uploads/sites/81/2022/07/Image_8-1-600x316.jpg","category":"BMW 3 Series","brandId":{"$oid":"67ce91ac426de9e0ddc8332a"},"pricePerDay":24,"des":"Ut urna et consequat porttitor arcu habitasse sed amet tortor.","createdAt":{"$date":"2025-03-10T07:21:03.275Z"},"updatedAt":{"$date":"2025-03-10T07:21:03.275Z"},"__v":0}
{"_id":{"$oid":"67ce93fd6b08f021f96ec4b1"},"img":"https://xstore.b-cdn.net/elementor/demos/rental-car/wp-content/uploads/sites/81/2022/07/Image_4-1-600x316.jpg","category":"Mercedes A-Class","brandId":{"$oid":"67ce91ac426de9e0ddc8332a"},"pricePerDay":64,"des":"Sapien at nunc viverra sed quam facilisis ultrices varius sit.","createdAt":{"$date":"2025-03-10T07:25:49.486Z"},"updatedAt":{"$date":"2025-03-10T07:25:49.486Z"},"__v":0}
{"_id":{"$oid":"67ce99918c6d774332cd9366"},"img":"https://xstore.b-cdn.net/elementor/demos/rental-car/wp-content/uploads/sites/81/2022/07/Image_11-600x316.jpg","category":"Mercedes Benz","brandId":{"$oid":"67ce99768c6d774332cd9364"},"pricePerDay":34,"des":"Hendrerit viv amus justo maecenas senectus aliquam.","createdAt":{"$date":"2025-03-10T07:49:37.229Z"},"updatedAt":{"$date":"2025-03-10T07:49:37.229Z"},"__v":0}
{"_id":{"$oid":"67ce99e18c6d774332cd9368"},"img":"https://xstore.b-cdn.net/elementor/demos/rental-car/wp-content/uploads/sites/81/2022/07/Image_9-1-600x316.jpg","category":"Mercedes Z-Class","brandId":{"$oid":"67ce92ab426de9e0ddc8332c"},"pricePerDay":62,"des":"Sapien at nunc viverra sed quam facilisis ultrices varius sit.","createdAt":{"$date":"2025-03-10T07:50:57.518Z"},"updatedAt":{"$date":"2025-03-10T07:50:57.518Z"},"__v":0}
{"_id":{"$oid":"67ce9a2c8c6d774332cd936a"},"img":"https://xstore.b-cdn.net/elementor/demos/rental-car/wp-content/uploads/sites/81/2022/07/Image_3-600x316.jpeg","category":"Tesla Model","brandId":{"$oid":"67cd240be895c5e5487f531f"},"pricePerDay":60,"des":"Sapien at nu nc viverra sed quam facilisis ultrices varius sit.","createdAt":{"$date":"2025-03-10T07:52:12.101Z"},"updatedAt":{"$date":"2025-03-10T07:52:12.101Z"},"__v":0}
{"_id":{"$oid":"67ce9a6c8c6d774332cd936c"},"img":"https://xstore.b-cdn.net/elementor/demos/rental-car/wp-content/uploads/sites/81/2022/07/Image_10-600x316.jpg","category":"Tesla Model 3-Plaid","brandId":{"$oid":"67cd240be895c5e5487f531f"},"pricePerDay":35,"des":"Fames pharetra, quam porta semper mattis elementum faucibus elit.","createdAt":{"$date":"2025-03-10T07:53:16.08Z"},"updatedAt":{"$date":"2025-03-10T07:53:16.08Z"},"__v":0}
{"_id":{"$oid":"67ce9ab78c6d774332cd936e"},"img":"https://xstore.b-cdn.net/elementor/demos/rental-car/wp-content/uploads/sites/81/2022/07/Image_2-600x316.jpeg","category":"Volkswagen New Polo","brandId":{"$oid":"67ce92ab426de9e0ddc8332c"},"pricePerDay":58,"des":"Sap ien at nunc viverra sed quam facilisis ultrices varius sit.","createdAt":{"$date":"2025-03-10T07:54:31.979Z"},"updatedAt":{"$date":"2025-03-10T07:54:31.979Z"},"__v":0}
{"_id":{"$oid":"67ce9af68c6d774332cd9370"},"img":"https://xstore.b-cdn.net/elementor/demos/rental-car/wp-content/uploads/sites/81/2022/07/Image_1-600x316.jpeg","category":"Volkswagen Polo","brandId":{"$oid":"67ce92ab426de9e0ddc8332c"},"pricePerDay":40,"des":"Sap ien at nunc viverra sed quam facilisis ultrices varius sit.","createdAt":{"$date":"2025-03-10T07:55:34.356Z"},"updatedAt":{"$date":"2025-03-10T07:55:34.356Z"},"__v":0}
{"_id":{"$oid":"67ce9d348c6d774332cd937e"},"img":"https://xstore.b-cdn.net/elementor/demos/rental-car/wp-content/uploads/sites/81/2022/07/Image_6-1-600x316.jpg","category":"Audi Speed A4","brandId":{"$oid":"67ce99768c6d774332cd9364"},"pricePerDay":33,"des":"Ullamcorper placerat tincidunt fringilla dignissim leo in et nisl. ","createdAt":{"$date":"2025-03-10T08:05:08.378Z"},"updatedAt":{"$date":"2025-03-24T09:01:00.143Z"},"__v":0}
